ProdNet/__init__.py
ProdNet/lib.py
ProdNet/models.py
ProdNet-0.0.2.dist-info/LICENSE.txt
ProdNet-0.0.2.dist-info/METADATA
ProdNet-0.0.2.dist-info/WHEEL
ProdNet-0.0.2.dist-info/top_level.txt
ProdNet-0.0.2.dist-info/RECORD
