Metadata-Version: 2.1
Name: ProdNet
Version: 0.0.2
Summary: A collection of models of economic Production Networks and their associated measures and functions.
Home-page: https://github.com/LeonardoIalongo/ProdNet
Author: Leonardo Niccolò Ialongo, Davide Luzzati
Author-email: leonardo.ialongo@gmail.com
License: GNU General Public License v3
Classifier: Development Status :: 2 - Pre-Alpha
Classifier: License :: OSI Approved :: GNU General Public License v3 (GPLv3)
Classifier: Natural Language :: English
Classifier: Programming Language :: Python :: 3
Classifier: Programming Language :: Python :: 3.7
Classifier: Programming Language :: Python :: 3.8
Classifier: Programming Language :: Python :: 3.9
Classifier: Operating System :: OS Independent
Requires-Python: >=3.0
License-File: LICENSE.txt
Requires-Dist: numpy >=1.22
Requires-Dist: numba >=0.58
Requires-Dist: scipy >=1.6
